<annotation>
	<folder>dark</folder>
	<filename>October192021152439493646.mp42022-01-25-13h47m46s027.png</filename>
	<path>C:\Users\MGS\Documents\GitHub\bias_project\UIC\dark\October192021152439493646.mp42022-01-25-13h47m46s027.png</path>
	<source>
		<database>Unknown</database>
	</source>
	<size>
		<width>1920</width>
		<height>1080</height>
		<depth>3</depth>
	</size>
	<segmented>0</segmented>
	<object>
		<name>pupil</name>
		<pose>Unspecified</pose>
		<truncated>0</truncated>
		<difficult>0</difficult>
		<bndbox>
			<xmin>442</xmin>
			<ymin>172</ymin>
			<xmax>1060</xmax>
			<ymax>753</ymax>
		</bndbox>
	</object>
	<object>
		<name>iris</name>
		<pose>Unspecified</pose>
		<truncated>0</truncated>
		<difficult>0</difficult>
		<bndbox>
			<xmin>268</xmin>
			<ymin>5</ymin>
			<xmax>1316</xmax>
			<ymax>1041</ymax>
		</bndbox>
	</object>
</annotation>
